{"stats":{"minecraft:picked_up":{"minecraft:bone":2,"minecraft:wheat_seeds":3,"minecraft:mutton":6,"minecraft:white_wool":4},"minecraft:killed":{"minecraft:sheep":2,"minecraft:skeleton":1},"minecraft:mined":{"minecraft:grass":3,"minecraft:tall_grass":1},"minecraft:dropped":{"minecraft:wheat_seeds":3,"minecraft:mutton":6,"minecraft:bone":2},"minecraft:custom":{"minecraft:time_since_rest":3417,"minecraft:crouch_one_cm":29,"minecraft:play_time":3417,"minecraft:sprint_one_cm":9328,"minecraft:damage_taken":85,"minecraft:walk_one_cm":3527,"minecraft:sneak_time":42,"minecraft:walk_under_water_one_cm":460,"minecraft:mob_kills":3,"minecraft:drop":3,"minecraft:jump":110,"minecraft:damage_dealt":378,"minecraft:leave_game":1,"minecraft:walk_on_water_one_cm":126,"minecraft:time_since_death":3417,"minecraft:total_world_time":3417,"minecraft:swim_one_cm":1362,"minecraft:fly_one_cm":61956,"minecraft:fall_one_cm":3597}},"DataVersion":3465}